Workbook

Sheet BoM por modulo
A1: BoM AFE sEMG AuraVox: 4 canales, 9 electrodos, RLD. Ordenada por modulo, igual que los recuadros del esquematico LTspice (sim/ltspice).
A2: Celdas amarillas = las llenas tu (tienda, precio, estado). Las cantidades y subtotales se calculan solos.
A4: Modulo | B4: Ref. en esquematico | C4: Componente | D4: Valor de diseno | E4: Valor a comprar | F4: Tipo / tolerancia | G4: Cant. por canal | H4: N canales | I4: Cant. total | J4: Repuesto | K4: A comprar | L4: Buscar como | M4: Tienda | N4: Precio unit. (CLP) | O4: Subtotal (CLP) | P4: Estado | Q4: Notas
A5: 1 PROTECCION ESD | C5: por canal (x4)
A6: 1 PROTECCION ESD | B6: Rsp, Rsn | C6: Resistencia serie de entrada | D6: 100k | E6: 100k | F6: pelicula metalica 1 % 1/4 W | G6: 2 | H6: 4 | I6: =G6*H6 -> 8 | J6: 2 | K6: =I6+J6 -> 10 | L6: resistencia 100k 1% 1/4W | O6: =IF(N6="","",K6*N6) | P6: Pendiente | Q6: Limita la corriente de falla hacia el paciente y hacia el INA
A7: 1 PROTECCION ESD | B7: Dp1, Dp2, Dn1, Dn2 | C7: Diodo de clamp a VCC y GND | D7: 1N4148 | E7: 1N4148 | F7: diodo de senal | G7: 4 | H7: 4 | I7: =G7*H7 -> 16 | J7: 4 | K7: =I7+J7 -> 20 | L7: 1N4148 | O7: =IF(N7="","",K7*N7) | P7: Pendiente | Q7: 4 por canal x 4 = 16 (+4 repuesto = 20). Protegen el INA de descargas
A8: 2 FILTRO RFI | C8: por canal (x4)
A9: 2 FILTRO RFI | B9: Rfp, Rfn | C9: Resistencia del filtro RFI | D9: 1k | E9: 1k | F9: pelicula metalica 1 % | G9: 2 | H9: 4 | I9: =G9*H9 -> 8 | J9: 2 | K9: =I9+J9 -> 10 | L9: resistencia 1k 1% | O9: =IF(N9="","",K9*N9) | P9: Pendiente
A10: 2 FILTRO RFI | B10: Ccmp, Ccmn | C10: Condensador de modo comun | D10: 47p | E10: 47p | F10: ceramico C0G/NP0 5 % | G10: 2 | H10: 4 | I10: =G10*H10 -> 8 | J10: 2 | K10: =I10+J10 -> 10 | L10: condensador ceramico 47pF NP0 | O10: =IF(N10="","",K10*N10) | P10: Pendiente | Q10: Si la simulacion final elige 330k sin Ccm, no se usan
A11: 2 FILTRO RFI | B11: Cdif | C11: Condensador diferencial | D11: 100p | E11: 100p | F11: ceramico C0G/NP0 5 % | G11: 1 | H11: 4 | I11: =G11*H11 -> 4 | J11: 1 | K11: =I11+J11 -> 5 | L11: condensador ceramico 100pF NP0 | O11: =IF(N11="","",K11*N11) | P11: Pendiente
A12: 3 AMPLIFICADOR DE INSTRUMENTACION | C12: por canal (x4)
A13: 3 AMPLIFICADOR DE INSTRUMENTACION | B13: XINA | C13: INA (POR DEFINIR, ver hoja Requisitos IC) | D13: INA333 | E13: INA333 / AD623 / AD8226 / INA826 | F13: DIP-8 o modulo con RG accesible | G13: 1 | H13: 4 | I13: =G13*H13 -> 4 | J13: 1 | K13: =I13+J13 -> 5 | L13: INA333 o AD623AN DIP-8 | O13: =IF(N13="","",K13*N13) | P13: Pendiente | Q13: G1 = 1 + 100k/RG para INA333/AD623/AD8226/INA826
A14: 3 AMPLIFICADOR DE INSTRUMENTACION | B14: RGa, RGb | C14: Resistencia de ganancia (partida en dos) | D14: 2.61k | E14: 2.7k | F14: pelicula metalica 1 %, parear con multimetro | G14: 2 | H14: 4 | I14: =G14*H14 -> 8 | J14: 4 | K14: =I14+J14 -> 12 | L14: resistencia 2.7k 1% | O14: =IF(N14="","",K14*N14) | P14: Pendiente | Q14: Con 2 x 2.7k: G1 = 19.5 (diseno 20.16). El punto medio va al RLD
A15: 3 AMPLIFICADOR DE INSTRUMENTACION | B15: C desac. INA | C15: Desacople del INA | D15: 100n | E15: 100n | F15: ceramico X7R | G15: 1 | H15: 4 | I15: =G15*H15 -> 4 | J15: 1 | K15: =I15+J15 -> 5 | L15: condensador ceramico 100nF | O15: =IF(N15="","",K15*N15) | P15: Pendiente | Q15: Pegado al pin de alimentacion
A16: 4 HPF 20 Hz (Sallen-Key) | C16: por canal (x4)
A17: 4 HPF 20 Hz (Sallen-Key) | B17: Chp1, Chp2 | C17: Condensador del HPF | D17: 100n | E17: 100n | F17: poliester/MKT (film) 5 % | G17: 2 | H17: 4 | I17: =G17*H17 -> 8 | J17: 2 | K17: =I17+J17 -> 10 | L17: condensador poliester 100nF 5% | O17: =IF(N17="","",K17*N17) | P17: Pendiente | Q17: Film, no ceramico: estabilidad y bajo ruido
A18: 4 HPF 20 Hz (Sallen-Key) | B18: R1 | C18: Resistencia de realimentacion | D18: 56.2k | E18: 56k | F18: pelicula metalica 1 % | G18: 1 | H18: 4 | I18: =G18*H18 -> 4 | J18: 1 | K18: =I18+J18 -> 5 | L18: resistencia 56k 1% | O18: =IF(N18="","",K18*N18) | P18: Pendiente | Q18: Con 56k/110k: f0 = 20.3 Hz, Q = 0.70
A19: 4 HPF 20 Hz (Sallen-Key) | B19: Ra | C19: Resistencia a VREF | D19: 113k | E19: 110k | F19: pelicula metalica 1 % | G19: 1 | H19: 4 | I19: =G19*H19 -> 4 | J19: 1 | K19: =I19+J19 -> 5 | L19: resistencia 110k 1% | O19: =IF(N19="","",K19*N19) | P19: Pendiente
A20: 4 HPF 20 Hz (Sallen-Key) | B20: XHP | C20: seccion de op-amp | D20: - | E20: - | F20: - | Q20: Contada en el modulo 11 OP-AMPS
A21: 5 G2 = 25 | C21: por canal (x4)
A22: 5 G2 = 25 | B22: Rf | C22: Resistencia de realimentacion | D22: 240k | E22: 240k | F22: pelicula metalica 1 % | G22: 1 | H22: 4 | I22: =G22*H22 -> 4 | J22: 1 | K22: =I22+J22 -> 5 | L22: resistencia 240k 1% | O22: =IF(N22="","",K22*N22) | P22: Pendiente
A23: 5 G2 = 25 | B23: Rg | C23: Resistencia de ganancia | D23: 10k | E23: 10k | F23: pelicula metalica 1 % | G23: 1 | H23: 4 | I23: =G23*H23 -> 4 | J23: 1 | K23: =I23+J23 -> 5 | L23: resistencia 10k 1% | O23: =IF(N23="","",K23*N23) | P23: Pendiente
A24: 5 G2 = 25 | B24: Cg | C24: Condensador de bloqueo DC (G = 1 en DC) | D24: 10u | E24: 10u | F24: ceramico X7R o electrolitico 16 V | G24: 1 | H24: 4 | I24: =G24*H24 -> 4 | J24: 1 | K24: =I24+J24 -> 5 | L24: condensador 10uF | O24: =IF(N24="","",K24*N24) | P24: Pendiente
A25: 5 G2 = 25 | B25: XG2 | C25: seccion de op-amp | D25: - | E25: - | F25: - | Q25: Contada en el modulo 11 OP-AMPS
A26: 6 LPF A 500 Hz (Q 0.541) | C26: por canal (x4)
A27: 6 LPF A 500 Hz (Q 0.541) | B27: Rla1, Rla2 | C27: Resistencia del LPF A | D27: 88.7k | E27: 91k | F27: pelicula metalica 1 % | G27: 2 | H27: 4 | I27: =G27*H27 -> 8 | J27: 2 | K27: =I27+J27 -> 10 | L27: resistencia 91k 1% | O27: =IF(N27="","",K27*N27) | P27: Pendiente | Q27: Con 91k: f0 = 487 Hz
A28: 6 LPF A 500 Hz (Q 0.541) | B28: C11 | C28: Condensador de realimentacion | D28: 3.9n | E28: 3.9n | F28: poliester 5 % o C0G | G28: 1 | H28: 4 | I28: =G28*H28 -> 4 | J28: 1 | K28: =I28+J28 -> 5 | L28: condensador poliester 3.9nF | O28: =IF(N28="","",K28*N28) | P28: Pendiente
A29: 6 LPF A 500 Hz (Q 0.541) | B29: C12 | C29: Condensador a GND | D29: 3.3n | E29: 3.3n | F29: poliester 5 % o C0G | G29: 1 | H29: 4 | I29: =G29*H29 -> 4 | J29: 1 | K29: =I29+J29 -> 5 | L29: condensador poliester 3.3nF | O29: =IF(N29="","",K29*N29) | P29: Pendiente
A30: 6 LPF A 500 Hz (Q 0.541) | B30: XLA | C30: seccion de op-amp | D30: - | E30: - | F30: - | Q30: Contada en el modulo 11 OP-AMPS
A31: 7 LPF B 500 Hz (Q 1.306) | C31: por canal (x4)
A32: 7 LPF B 500 Hz (Q 1.306) | B32: Rlb1, Rlb2 | C32: Resistencia del LPF B | D32: 54.9k | E32: 56k | F32: pelicula metalica 1 % | G32: 2 | H32: 4 | I32: =G32*H32 -> 8 | J32: 2 | K32: =I32+J32 -> 10 | L32: resistencia 56k 1% | O32: =IF(N32="","",K32*N32) | P32: Pendiente | Q32: Con 56k: f0 = 495 Hz
A33: 7 LPF B 500 Hz (Q 1.306) | B33: C21 | C33: Condensador de realimentacion | D33: 15n | E33: 15n | F33: poliester 5 % o C0G | G33: 1 | H33: 4 | I33: =G33*H33 -> 4 | J33: 1 | K33: =I33+J33 -> 5 | L33: condensador poliester 15nF | O33: =IF(N33="","",K33*N33) | P33: Pendiente
A34: 7 LPF B 500 Hz (Q 1.306) | B34: C22 | C34: Condensador a GND | D34: 2.2n | E34: 2.2n | F34: poliester 5 % o C0G | G34: 1 | H34: 4 | I34: =G34*H34 -> 4 | J34: 1 | K34: =I34+J34 -> 5 | L34: condensador poliester 2.2nF | O34: =IF(N34="","",K34*N34) | P34: Pendiente
A35: 7 LPF B 500 Hz (Q 1.306) | B35: XLB | C35: seccion de op-amp | D35: - | E35: - | F35: - | Q35: Contada en el modulo 11 OP-AMPS
A36: 8 BUFFER + SALIDA AL ADC | C36: por canal (x4)
A37: 8 BUFFER + SALIDA AL ADC | B37: Rbk | C37: Resistencia del bucket | D37: 100 | E37: 100 | F37: pelicula metalica 1 % | G37: 1 | H37: 4 | I37: =G37*H37 -> 4 | J37: 1 | K37: =I37+J37 -> 5 | L37: resistencia 100 ohm 1% | O37: =IF(N37="","",K37*N37) | P37: Pendiente
A38: 8 BUFFER + SALIDA AL ADC | B38: Cbk | C38: Condensador del bucket | D38: 1n | E38: 1n | F38: ceramico C0G/NP0 | G38: 1 | H38: 4 | I38: =G38*H38 -> 4 | J38: 1 | K38: =I38+J38 -> 5 | L38: condensador ceramico 1nF NP0 | O38: =IF(N38="","",K38*N38) | P38: Pendiente
A39: 8 BUFFER + SALIDA AL ADC | B39: ADCk | C39: Cable a Arduino A0..A3 del STM32N6570-DK | D39: - | E39: jumper Dupont | F39: - | G39: 1 | H39: 4 | I39: =G39*H39 -> 4 | J39: 2 | K39: =I39+J39 -> 6 | L39: cable dupont macho-macho | O39: =IF(N39="","",K39*N39) | P39: Pendiente | Q39: CH1-A0 (PA5), CH2-A1 (PA9), CH3-A2 (PA10), CH4-A3 (PA12). Mas 1 cable de GND
A40: 8 BUFFER + SALIDA AL ADC | B40: XBF | C40: seccion de op-amp | D40: - | E40: - | F40: - | Q40: Contada en el modulo 11 OP-AMPS
A41: 9 VREF 1.65 V (compartido) | C41: compartido
A42: 9 VREF 1.65 V (compartido) | B42: RA1, RA2 | C42: Divisor de VREF | D42: 100k | E42: 100k | F42: pelicula metalica 1 % | G42: 2 | H42: 1 | I42: =G42*H42 -> 2 | J42: 0 | K42: =I42+J42 -> 2 | L42: resistencia 100k 1% | O42: =IF(N42="","",K42*N42) | P42: Pendiente
A43: 9 VREF 1.65 V (compartido) | B43: CA | C43: Condensador del divisor | D43: 10u | E43: 10u | F43: ceramico X7R o electrolitico | G43: 1 | H43: 1 | I43: =G43*H43 -> 1 | J43: 0 | K43: =I43+J43 -> 1 | L43: condensador 10uF | O43: =IF(N43="","",K43*N43) | P43: Pendiente
A44: 9 VREF 1.65 V (compartido) | B44: XVR | C44: seccion de op-amp | D44: - | E44: - | F44: - | Q44: Contada en el modulo 11 OP-AMPS
A45: 10 RLD (compartido) | C45: compartido
A46: 10 RLD (compartido) | B46: RSM1..RSM4 | C46: Sensado de modo comun (punto medio de RG) | D46: 604k | E46: 620k | F46: pelicula metalica 1 % | G46: 4 | H46: 1 | I46: =G46*H46 -> 4 | J46: 1 | K46: =I46+J46 -> 5 | L46: resistencia 620k 1% | O46: =IF(N46="","",K46*N46) | P46: Pendiente
A47: 10 RLD (compartido) | B47: CINT | C47: Condensador del integrador | D47: 1n | E47: 1n | F47: ceramico C0G/NP0 | G47: 1 | H47: 1 | I47: =G47*H47 -> 1 | J47: 1 | K47: =I47+J47 -> 2 | L47: condensador ceramico 1nF NP0 | O47: =IF(N47="","",K47*N47) | P47: Pendiente | Q47: Si oscila en banco: 2.2n
A48: 10 RLD (compartido) | B48: RPAR | C48: Resistencia en paralelo al integrador | D48: 10M | E48: 10M | F48: pelicula 5 % | G48: 1 | H48: 1 | I48: =G48*H48 -> 1 | J48: 1 | K48: =I48+J48 -> 2 | L48: resistencia 10M | O48: =IF(N48="","",K48*N48) | P48: Pendiente
A49: 10 RLD (compartido) | B49: RLIM | C49: Resistencia de seguridad al electrodo RLD | D49: 390k | E49: 390k | F49: pelicula metalica 1 % | G49: 1 | H49: 1 | I49: =G49*H49 -> 1 | J49: 1 | K49: =I49+J49 -> 2 | L49: resistencia 390k 1% | O49: =IF(N49="","",K49*N49) | P49: Pendiente | Q49: Limita la corriente al paciente
A50: 10 RLD (compartido) | B50: XRLD | C50: seccion de op-amp | D50: - | E50: - | F50: - | Q50: Contada en el modulo 11 OP-AMPS
A51: 11 OP-AMPS (paquetes) | C51: compartido
A52: 11 OP-AMPS (paquetes) | B52: XHP..XBF x4, XRLD, XVR | C52: Op-amp cuadruple (POR DEFINIR, ver hoja Requisitos IC) | D52: MCP6004 | E52: cuadruple rail-to-rail | F52: DIP-14 | G52: 6 | H52: 1 | I52: =G52*H52 -> 6 | J52: 1 | K52: =I52+J52 -> 7 | L52: MCP6004 / MCP604 / TLV2374 / OPA4340 | O52: =IF(N52="","",K52*N52) | P52: Pendiente | Q52: 22 secciones = 5 por canal x 4 + RLD + VREF (2 libres). Si es doble: 11 unidades DIP-8
A53: 11 OP-AMPS (paquetes) | B53: - | C53: Zocalo DIP-14 | D53: - | E53: DIP-14 | F53: zocalo | G53: 6 | H53: 1 | I53: =G53*H53 -> 6 | J53: 1 | K53: =I53+J53 -> 7 | L53: zocalo DIP 14 pines | O53: =IF(N53="","",K53*N53) | P53: Pendiente | Q53: Si los op-amps son dobles: 11 zocalos DIP-8
A54: 11 OP-AMPS (paquetes) | B54: - | C54: Desacople de cada op-amp | D54: 100n | E54: 100n | F54: ceramico X7R | G54: 6 | H54: 1 | I54: =G54*H54 -> 6 | J54: 2 | K54: =I54+J54 -> 8 | L54: condensador ceramico 100nF | O54: =IF(N54="","",K54*N54) | P54: Pendiente | Q54: Pegado al pin de alimentacion
A55: 12 ALIMENTACION (a bateria) | C55: compartido
A56: 12 ALIMENTACION (a bateria) | B56: - | C56: Regulador LDO 3.3 V | D56: MCP1700-3302E | E56: MCP1700-3302E TO-92 | F56: LDO 250 mA | G56: 1 | H56: 1 | I56: =G56*H56 -> 1 | J56: 1 | K56: =I56+J56 -> 2 | L56: MCP1700 3.3V TO-92 | M56: HUBOT | N56: 890 | O56: =IF(N56="","",K56*N56) -> 1780 | P56: Pendiente | Q56: EJEMPLO de llenado: CLP 890 c/IVA en hubot.cl (30-sep-2026). Tu LDO de 3.0 V no sirve
A57: 12 ALIMENTACION (a bateria) | B57: - | C57: Condensadores del LDO (entrada y salida) | D57: 1u | E57: 1u | F57: ceramico X7R | G57: 2 | H57: 1 | I57: =G57*H57 -> 2 | J57: 1 | K57: =I57+J57 -> 3 | L57: condensador ceramico 1uF | O57: =IF(N57="","",K57*N57) | P57: Pendiente | Q57: Ya tienes 2 x 1uF 0402 (SMD): sirven si los sueldas
A58: 12 ALIMENTACION (a bateria) | B58: - | C58: Condensador bulk del riel 3.3 V | D58: 10u | E58: 10u | F58: ceramico o electrolitico | G58: 1 | H58: 1 | I58: =G58*H58 -> 1 | J58: 1 | K58: =I58+J58 -> 2 | L58: condensador 10uF | O58: =IF(N58="","",K58*N58) | P58: Pendiente
A59: 12 ALIMENTACION (a bateria) | B59: - | C59: Portapilas 3 x AA | D59: - | E59: 3xAA | F59: - | G59: 1 | H59: 1 | I59: =G59*H59 -> 1 | J59: 0 | K59: =I59+J59 -> 1 | L59: portapilas 3 AA | O59: =IF(N59="","",K59*N59) | P59: Pendiente | Q59: 4.5 V nominal; mantiene el AFE aislado de la red
A60: 12 ALIMENTACION (a bateria) | B60: - | C60: Pilas AA | D60: - | E60: AA | F60: alcalina | G60: 3 | H60: 1 | I60: =G60*H60 -> 3 | J60: 3 | K60: =I60+J60 -> 6 | L60: pila AA | O60: =IF(N60="","",K60*N60) | P60: Pendiente
A61: 12 ALIMENTACION (a bateria) | B61: - | C61: Interruptor | D61: - | E61: deslizante | F61: - | G61: 1 | H61: 1 | I61: =G61*H61 -> 1 | J61: 0 | K61: =I61+J61 -> 1 | L61: interruptor deslizante | O61: =IF(N61="","",K61*N61) | P61: Pendiente
A62: 13 ELECTRODOS Y CABLES | C62: compartido
A63: 13 ELECTRODOS Y CABLES | B63: XE1P..XE4N, XER | C63: Electrodo Ag/AgCl con broche | D63: - | E63: 3M Red Dot 2228/2560 | F63: desechable | G63: 9 | H63: 1 | I63: =G63*H63 -> 9 | J63: 41 | K63: =I63+J63 -> 50 | L63: electrodo ECG 3M 2228 | O63: =IF(N63="","",K63*N63) | P63: Pendiente | Q63: 9 por sesion (8 de senal + 1 RLD); caja de 50
A64: 13 ELECTRODOS Y CABLES | B64: - | C64: Cable con broche (snap) para electrodo | D64: - | E64: broche 4 mm | F64: - | G64: 9 | H64: 1 | I64: =G64*H64 -> 9 | J64: 1 | K64: =I64+J64 -> 10 | L64: cable electrodo broche snap | O64: =IF(N64="","",K64*N64) | P64: Pendiente | Q64: O 3 cables ECG de 3 derivaciones
A65: 13 ELECTRODOS Y CABLES | B65: - | C65: Alcohol isopropilico / gel | D65: - | E65: - | F65: - | G65: 1 | H65: 1 | I65: =G65*H65 -> 1 | J65: 0 | K65: =I65+J65 -> 1 | L65: alcohol isopropilico | O65: =IF(N65="","",K65*N65) | P65: Pendiente | Q65: Preparar la piel
A66: 14 MECANICA E INTERCONEXION | C66: compartido
A67: 14 MECANICA E INTERCONEXION | B67: - | C67: Perfboard | D67: - | E67: 10 x 15 cm | F67: fibra de vidrio | G67: 1 | H67: 1 | I67: =G67*H67 -> 1 | J67: 1 | K67: =I67+J67 -> 2 | L67: placa perforada 10x15 | O67: =IF(N67="","",K67*N67) | P67: Pendiente
A68: 14 MECANICA E INTERCONEXION | B68: - | C68: Zocalo DIP-8 (INA) | D68: - | E68: DIP-8 | F68: zocalo | G68: 4 | H68: 1 | I68: =G68*H68 -> 4 | J68: 1 | K68: =I68+J68 -> 5 | L68: zocalo DIP 8 pines | O68: =IF(N68="","",K68*N68) | P68: Pendiente | Q68: Solo si el INA es DIP-8
A69: 14 MECANICA E INTERCONEXION | B69: - | C69: Adaptador SOIC/MSOP-8 a DIP-8 | D69: - | E69: - | F69: PCB adaptador | G69: 4 | H69: 1 | I69: =G69*H69 -> 4 | J69: 1 | K69: =I69+J69 -> 5 | L69: adaptador SOIC8 a DIP8 | O69: =IF(N69="","",K69*N69) | P69: Pendiente | Q69: Solo si el INA es SMD
A70: 14 MECANICA E INTERCONEXION | B70: - | C70: Tira de headers macho/hembra | D70: - | E70: 2.54 mm | F70: - | G70: 2 | H70: 1 | I70: =G70*H70 -> 2 | J70: 1 | K70: =I70+J70 -> 3 | L70: header 2.54mm 40 pines | O70: =IF(N70="","",K70*N70) | P70: Pendiente
A71: 14 MECANICA E INTERCONEXION | B71: - | C71: Cable para puentes | D71: - | E71: 24 AWG rigido | F71: - | G71: 1 | H71: 1 | I71: =G71*H71 -> 1 | J71: 0 | K71: =I71+J71 -> 1 | L71: cable rigido 24 AWG | O71: =IF(N71="","",K71*N71) | P71: Pendiente
N73: TOTAL | O73: =SUM(O5:O71) -> 1780

Sheet Resumen
A1: Resumen por modulo
A3: Modulo | B3: Items | C3: Pendientes | D3: Subtotal (CLP)
A4: 1 PROTECCION ESD | B4: =COUNTIFS('BoM por modulo'!$A$5:$A$71,A4,'BoM por modulo'!$P$5:$P$71,"<>") -> 2 | C4: =COUNTIFS('BoM por modulo'!$A$5:$A$71,A4,'BoM por modulo'!$P$5:$P$71,"Pendiente") -> 2 | D4: =SUMIF('BoM por modulo'!$A$5:$A$71,A4,'BoM por modulo'!$O$5:$O$71) -> 0
A5: 2 FILTRO RFI | B5: =COUNTIFS('BoM por modulo'!$A$5:$A$71,A5,'BoM por modulo'!$P$5:$P$71,"<>") -> 3 | C5: =COUNTIFS('BoM por modulo'!$A$5:$A$71,A5,'BoM por modulo'!$P$5:$P$71,"Pendiente") -> 3 | D5: =SUMIF('BoM por modulo'!$A$5:$A$71,A5,'BoM por modulo'!$O$5:$O$71) -> 0
A6: 3 AMPLIFICADOR DE INSTRUMENTACION | B6: =COUNTIFS('BoM por modulo'!$A$5:$A$71,A6,'BoM por modulo'!$P$5:$P$71,"<>") -> 3 | C6: =COUNTIFS('BoM por modulo'!$A$5:$A$71,A6,'BoM por modulo'!$P$5:$P$71,"Pendiente") -> 3 | D6: =SUMIF('BoM por modulo'!$A$5:$A$71,A6,'BoM por modulo'!$O$5:$O$71) -> 0
A7: 4 HPF 20 Hz (Sallen-Key) | B7: =COUNTIFS('BoM por modulo'!$A$5:$A$71,A7,'BoM por modulo'!$P$5:$P$71,"<>") -> 3 | C7: =COUNTIFS('BoM por modulo'!$A$5:$A$71,A7,'BoM por modulo'!$P$5:$P$71,"Pendiente") -> 3 | D7: =SUMIF('BoM por modulo'!$A$5:$A$71,A7,'BoM por modulo'!$O$5:$O$71) -> 0
A8: 5 G2 = 25 | B8: =COUNTIFS('BoM por modulo'!$A$5:$A$71,A8,'BoM por modulo'!$P$5:$P$71,"<>") -> 3 | C8: =COUNTIFS('BoM por modulo'!$A$5:$A$71,A8,'BoM por modulo'!$P$5:$P$71,"Pendiente") -> 3 | D8: =SUMIF('BoM por modulo'!$A$5:$A$71,A8,'BoM por modulo'!$O$5:$O$71) -> 0
A9: 6 LPF A 500 Hz (Q 0.541) | B9: =COUNTIFS('BoM por modulo'!$A$5:$A$71,A9,'BoM por modulo'!$P$5:$P$71,"<>") -> 3 | C9: =COUNTIFS('BoM por modulo'!$A$5:$A$71,A9,'BoM por modulo'!$P$5:$P$71,"Pendiente") -> 3 | D9: =SUMIF('BoM por modulo'!$A$5:$A$71,A9,'BoM por modulo'!$O$5:$O$71) -> 0
A10: 7 LPF B 500 Hz (Q 1.306) | B10: =COUNTIFS('BoM por modulo'!$A$5:$A$71,A10,'BoM por modulo'!$P$5:$P$71,"<>") -> 3 | C10: =COUNTIFS('BoM por modulo'!$A$5:$A$71,A10,'BoM por modulo'!$P$5:$P$71,"Pendiente") -> 3 | D10: =SUMIF('BoM por modulo'!$A$5:$A$71,A10,'BoM por modulo'!$O$5:$O$71) -> 0
A11: 8 BUFFER + SALIDA AL ADC | B11: =COUNTIFS('BoM por modulo'!$A$5:$A$71,A11,'BoM por modulo'!$P$5:$P$71,"<>") -> 3 | C11: =COUNTIFS('BoM por modulo'!$A$5:$A$71,A11,'BoM por modulo'!$P$5:$P$71,"Pendiente") -> 3 | D11: =SUMIF('BoM por modulo'!$A$5:$A$71,A11,'BoM por modulo'!$O$5:$O$71) -> 0
A12: 9 VREF 1.65 V (compartido) | B12: =COUNTIFS('BoM por modulo'!$A$5:$A$71,A12,'BoM por modulo'!$P$5:$P$71,"<>") -> 2 | C12: =COUNTIFS('BoM por modulo'!$A$5:$A$71,A12,'BoM por modulo'!$P$5:$P$71,"Pendiente") -> 2 | D12: =SUMIF('BoM por modulo'!$A$5:$A$71,A12,'BoM por modulo'!$O$5:$O$71) -> 0
A13: 10 RLD (compartido) | B13: =COUNTIFS('BoM por modulo'!$A$5:$A$71,A13,'BoM por modulo'!$P$5:$P$71,"<>") -> 4 | C13: =COUNTIFS('BoM por modulo'!$A$5:$A$71,A13,'BoM por modulo'!$P$5:$P$71,"Pendiente") -> 4 | D13: =SUMIF('BoM por modulo'!$A$5:$A$71,A13,'BoM por modulo'!$O$5:$O$71) -> 0
A14: 11 OP-AMPS (paquetes) | B14: =COUNTIFS('BoM por modulo'!$A$5:$A$71,A14,'BoM por modulo'!$P$5:$P$71,"<>") -> 3 | C14: =COUNTIFS('BoM por modulo'!$A$5:$A$71,A14,'BoM por modulo'!$P$5:$P$71,"Pendiente") -> 3 | D14: =SUMIF('BoM por modulo'!$A$5:$A$71,A14,'BoM por modulo'!$O$5:$O$71) -> 0
A15: 12 ALIMENTACION (a bateria) | B15: =COUNTIFS('BoM por modulo'!$A$5:$A$71,A15,'BoM por modulo'!$P$5:$P$71,"<>") -> 6 | C15: =COUNTIFS('BoM por modulo'!$A$5:$A$71,A15,'BoM por modulo'!$P$5:$P$71,"Pendiente") -> 6 | D15: =SUMIF('BoM por modulo'!$A$5:$A$71,A15,'BoM por modulo'!$O$5:$O$71) -> 1780
... A17: 14 MECANICA E INTERCONEXION | B17: =COUNTIFS('BoM por modulo'!$A$5:$A$71,A17,'BoM por modulo'!$P$5:$P$71,"<>") -> 5 | C17: =COUNTIFS('BoM por modulo'!$A$5:$A$71,A17,'BoM por modulo'!$P$5:$P$71,"Pendiente") -> 5 | D17: =SUMIF('BoM por modulo'!$A$5:$A$71,A17,'BoM por modulo'!$O$5:$O$71) -> 0
A18: TOTAL | B18: =SUM(B4:B17) -> 46 | C18: =SUM(C4:C17) -> 46 | D18: =SUM(D4:D17) -> 1780
A20: El total solo suma las filas con precio. Llena el precio en la hoja BoM por modulo.

Sheet Requisitos IC
A1: Condiciones que debe cumplir cada circuito integrado (para elegir reemplazos)
A3: OP-AMP (reemplazo del MCP6004): 22 secciones = HPF, G2, LPF A, LPF B y buffer en cada canal + RLD + VREF
A4: Parametro | B4: Requisito | C4: Por que (en este diseno)
A5: Alimentacion unica | B5: Funciona con 3.3 V: Vmin <= 3.0 V (ideal <= 2.7 V), Vmax >= 3.6 V | C5: Todo el AFE vive en 3.3 V a bateria
A6: Salida rail-to-rail | B6: Llega a <= 0.1 V de cada riel con 10 kohm | C6: La salida va de 0 a 3.3 V centrada en 1.65 V. LM358/LM324 no suben de ~1.8 V con 3.3 V
A7: Rango de entrada en modo comun | B7: Minimo 0.8-2.5 V (VREF +-0.85 V); ideal rail-to-rail | C7: En los filtros y buffers la entrada sigue a la salida
A8: Producto ganancia-ancho de banda (GBW) | B8: >= 0.5 MHz (ideal >= 1 MHz) | C8: G2 = 25 hasta 500 Hz y LPF con Q = 1.3
A9: Estable a ganancia 1 | B9: Si | C9: HPF, LPF y buffers son seguidores
A10: Corriente de polarizacion | B10: <= 10 nA (entrada CMOS ideal) | C10: Resistencias de 56-240 kohm: 10 nA x 110k = 1.1 mV
A11: Offset | B11: <= 5 mV | C11: G2 tiene ganancia 1 en DC: el offset no se amplifica
A12: Ruido de entrada | B12: <= 40 nV/rtHz | C12: Va despues de G1 = 20: no domina
A13: Consumo | B13: <= 0.5 mA por amplificador | C13: Bateria
A14: Encapsulado | B14: DIP-8/DIP-14, o SOIC con adaptador | C14: Perfboard
A15: SI sirven | B15: MCP6004/MCP6002, MCP604/MCP602, MCP6024/MCP6022, TLV2374/TLV2372, OPA4340/OPA2340, OPA4344/OPA2344, AD8608/AD8606
A16: Con reservas | B16: LMV324/LMV358 (entrada solo hasta V+ - 0.8 V; alcanza para +-0.85 V; suelen ser SMD)
A17: NO sirven | B17: LM358, LM324, TL071/TL072/TL074, NE5532, LM741, LF347, JRC4558, LM833, TLC2272 (no llegan a los rieles con 3.3 V o necesitan mas voltaje)
A19: INA (amplificador de instrumentacion): 4 unidades, una por canal
A20: Parametro | B20: Requisito | C20: Por que (en este diseno)
A21: Alimentacion unica | B21: Funciona con 3.3 V: Vmin <= 3.0 V | C21: Mismo riel que los op-amps
A22: Salida | B22: Rail-to-rail, o al menos 0.2-3.1 V | C22: La salida se centra en VREF = 1.65 V
A23: Rango de entrada en modo comun | B23: Debe incluir 1.4-1.9 V con alimentacion de 3.3 V | C23: El RLD mantiene el cuerpo en VREF = 1.65 V
A24: Ganancia | B24: Fijada por una sola RG, con los dos pines de RG accesibles | C24: El RLD sensa el punto medio de RG. Un modulo con potenciometro obliga a reemplazarlo por 2 resistencias
A25: Formula de ganancia | B25: G = 1 + 100k/RG: INA333, AD623, AD8226, INA826 (RG = 2 x 2.7k). INA122: G = 5 + 200k/RG. INA126: G = 5 + 80k/RG | C25: G1 objetivo ~20
A26: CMRR | B26: >= 90 dB a G = 20 (DC a 50 Hz) | C26: Rechazo del 50 Hz de la red
A27: Corriente de polarizacion | B27: <= 25 nA | C27: Con 100k de proteccion: <= 2.5 mV de offset
A28: Ruido de entrada | B28: <= 50 nV/rtHz | C28: Senal sEMG de 25-50 uV RMS
A29: Ancho de banda a G = 20 | B29: >= 5 kHz | C29: Banda util 20-500 Hz
A30: Encapsulado | B30: DIP-8, o SOIC/MSOP con adaptador, o modulo con RG accesible | C30: Perfboard
A31: SI sirven | B31: INA333 (ideal), AD8226, INA826
A32: Con reservas | B32: AD623 (modo comun max ~ Vs - 1.5 V = 1.8 V con 3.3 V: margen de 0.15 V sobre VREF); INA122/INA126 (recalcular RG) | C32: AD623AN DIP-8: 2 u por CLP 16.170 en Mercado Libre (30-sep-2026)
A33: NO sirven | B33: AD620, INA128, INA129, INA114, INA118 (necesitan ~4.6 V o mas y no tienen salida rail-to-rail); AD8232 (frontend completo de 1 canal, choca con el RLD compartido)
A35: LDO 3.3 V (alimentacion del AFE)
A36: Parametro | B36: Requisito | C36: Por que (en este diseno)
A37: Salida | B37: 3.3 V fija, >= 50 mA | C37: AFE completo consume < 10 mA
A38: Entrada | B38: Hasta >= 6 V; dropout <= 0.3 V a 20 mA | C38: 3 pilas AA = 4.5 V nueva, ~3.6 V gastada
A39: Estabilidad | B39: Estable con condensadores ceramicos
A40: SI sirven | B40: MCP1700-3302E (TO-92), MCP1702-3302, LP2950-3.3, HT7333 | C40: MCP1700: CLP 890 en hubot.cl
A41: Con reservas | B41: AMS1117-3.3 (dropout ~1.1 V: usar 4 pilas AA)
A42: NO sirve | B42: El LDO de 3.0 V que ya tienes

Sheet Tiendas
A1: Donde buscar (datos revisados el 30-sep-2026)
A3: Tienda | B3: Ubicacion | C3: Modalidad | D3: Que tiene / buscar | E3: Web
A4: Katode | B4: San Martin 133 E, Santiago Centro | C4: Retiro el mismo dia, L-V 9:30-14:00 | D4: Pasivos, zocalos, perfboard. Op-amps solo clasicos (TL07x, NE5532): NO sirven | E4: katode.cl
A5: HUBOT | B5: Santiago | C5: Despacho el mismo dia si se pide antes de las 12:30 | D5: MCP1700-3302E (CLP 890) | E5: hubot.cl
A6: MCI Electronics | B6: Santiago | C6: Retiro en tienda 8:30-17:30 | D6: Kits de resistencias 1 %, modulos | E6: mcielectronics.cl
A7: Afel | B7: Santiago | C7: Tienda y web | D7: Pasivos y kits | E7: afel.cl
A8: MechatronicStore | B8: Curico | C8: Envio; gratis sobre CLP 19.990 | D8: Modulo INA333 MCU-333 (CLP 6.790; RG es potenciometro), poliester | E8: mechatronicstore.cl
A9: Mercado Libre | B9: - | C9: Filtrar "Llega hoy" y vendedores de Santiago | D9: AD623AN DIP-8 (2 u CLP 16.170), electrodos 3M 2228, cables con broche | E9: mercadolibre.cl
A10: RS Chile | B10: - | C10: Web, plazos segun stock | D10: MCP6004-E/P CLP 809 c/IVA, minimo 30 u, sin stock al 30-sep | E10: cl.rsdelivers.com
A11: Klinetix | B11: Santiago | C11: Despacho 1-2 dias habiles en RM | D11: Electrodos 3M 2228 caja de 50 (agotado al 30-sep) | E11: klinetix.cl
A12: DigiKey / Mouser | B12: EE.UU. | C12: 2-5 dias habiles, impuestos al recibir | D12: Cualquier IC de la lista SI sirven | E12: digikey.com / mouser.cl
